Workbook

Sheet Start Here
B2: 2027 Net Worth Tracker
B3: One balance per account, once a month. The workbook does the totals, the change and the chart.
B5: HOW TO USE
B6: 1. Go to the Settings tab and type your net worth goal for Dec 31, 2027 (yellow cell).
B7: 2. Go to the Balances tab. List each account once: name, Type (Asset or Debt) and Category - both are drop-down lists.
B8: 3. In the Start column type each balance on Dec 31, 2026 (or the day you begin). Then add one balance per month, e.g. on the 1st.
B9: 4. Type debts as POSITIVE numbers (what you owe). The workbook subtracts them for you.
B10: 5. Open Summary for your monthly net worth, change, % of goal and the chart. By Category shows where the money sits.
B12: WHICH CELLS TO EDIT
B13: Yellow cells = your inputs. Everything else is a formula - no need to touch it. Months you have not filled in yet stay blank.
B14: Up to 40 accounts fit on the Balances tab. Leave unused rows empty.
B15: Works in Microsoft Excel and Google Sheets (File > Import > Upload in Google Sheets). Numbers show in $ but work for any currency.
... B23: This tracker is a personal organizing tool, not financial advice. This is the blank copy - an example-filled copy is included in the download.

Sheet Settings
B2: Settings
B4: Net worth goal for Dec 31, 2027 | C4: 0
B5: Emergency fund target (optional) | C5: 0
B7: The goal is used for '% of goal' on the Summary tab. The emergency fund target is compared with the 'Savings & Emergency Fund' category.

Sheet Balances
A1: Balances - one number per account per month
A2: Yellow = type here. Debts as positive numbers. Leave a month blank until you reach it.
A5: Account | B5: Type | C5: Category | D5: Start | E5: Jan | F5: Feb | G5: Mar | H5: Apr | I5: May | J5: Jun | K5: Jul | L5: Aug | M5: Sep | N5: Oct | O5: Nov | P5: Dec | Q5: Notes
A6: Checking account | B6: Asset | C6: Cash & Checking
A7: Savings account | B7: Asset | C7: Savings & Emergency Fund
A8: Investment account | B8: Asset | C8: Investments
A9: Retirement account | B9: Asset | C9: Retirement
A10: Credit card | B10: Debt | C10: Credit Cards
A11: Loan | B11: Debt | C11: Personal Loans
A47: Total assets | D47: =IF(COUNT(D6:D45)=0,"",SUMIF($B$6:$B$45,"Asset",D6:D45)) | E47: =IF(COUNT(E6:E45)=0,"",SUMIF($B$6:$B$45,"Asset",E6:E45)) | F47: =IF(COUNT(F6:F45)=0,"",SUMIF($B$6:$B$45,"Asset",F6:F45)) | G47: =IF(COUNT(G6:G45)=0,"",SUMIF($B$6:$B$45,"Asset",G6:G45)) | H47: =IF(COUNT(H6:H45)=0,"",SUMIF($B$6:$B$45,"Asset",H6:H45)) | I47: =IF(COUNT(I6:I45)=0,"",SUMIF($B$6:$B$45,"Asset",I6:I45)) | J47: =IF(COUNT(J6:J45)=0,"",SUMIF($B$6:$B$45,"Asset",J6:J45)) | K47: =IF(COUNT(K6:K45)=0,"",SUMIF($B$6:$B$45,"Asset",K6:K45)) | ... P47: =IF(COUNT(P6:P45)=0,"",SUMIF($B$6:$B$45,"Asset",P6:P45))
A48: Total debts | D48: =IF(COUNT(D6:D45)=0,"",SUMIF($B$6:$B$45,"Debt",D6:D45)) | E48: =IF(COUNT(E6:E45)=0,"",SUMIF($B$6:$B$45,"Debt",E6:E45)) | F48: =IF(COUNT(F6:F45)=0,"",SUMIF($B$6:$B$45,"Debt",F6:F45)) | G48: =IF(COUNT(G6:G45)=0,"",SUMIF($B$6:$B$45,"Debt",G6:G45)) | H48: =IF(COUNT(H6:H45)=0,"",SUMIF($B$6:$B$45,"Debt",H6:H45)) | I48: =IF(COUNT(I6:I45)=0,"",SUMIF($B$6:$B$45,"Debt",I6:I45)) | J48: =IF(COUNT(J6:J45)=0,"",SUMIF($B$6:$B$45,"Debt",J6:J45)) | K48: =IF(COUNT(K6:K45)=0,"",SUMIF($B$6:$B$45,"Debt",K6:K45)) | ... P48: =IF(COUNT(P6:P45)=0,"",SUMIF($B$6:$B$45,"Debt",P6:P45))
A49: Net worth | D49: =IF(D47="","",D47-D48) | E49: =IF(E47="","",E47-E48) | F49: =IF(F47="","",F47-F48) | G49: =IF(G47="","",G47-G48) | H49: =IF(H47="","",H47-H48) | I49: =IF(I47="","",I47-I48) | J49: =IF(J47="","",J47-J48) | K49: =IF(K47="","",K47-K48) | ... P49: =IF(P47="","",P47-P48)

Sheet Summary
A1: Summary - net worth month by month
A2: All formulas. Fill in the Balances tab and this page updates.
A4: Month | B4: Total assets | C4: Total debts | D4: Net worth | E4: Change vs last month | F4: Change since start | G4: % of goal | H4: Debts / assets | J4: Key figures
A5: Start (Dec 31, 2026) | B5: =Balances!D47 | C5: =Balances!D48 | D5: =Balances!D49 | E5: ="" | F5: =IF(OR(D5="",$D$5=""),"",D5-$D$5) | G5: =IF(OR(D5="",Settings!$C$4<=0),"",D5/Settings!$C$4) | H5: =IF(OR(B5="",N(B5)=0),"",C5/B5) | J5: Latest net worth | K5: =IF(COUNT(D5:D17)=0,"",LOOKUP(2,1/(D5:D17<>""),D5:D17))
A6: Jan 2027 | B6: =Balances!E47 | C6: =Balances!E48 | D6: =Balances!E49 | E6: =IF(OR(D6="",D5=""),"",D6-D5) | F6: =IF(OR(D6="",$D$5=""),"",D6-$D$5) | G6: =IF(OR(D6="",Settings!$C$4<=0),"",D6/Settings!$C$4) | H6: =IF(OR(B6="",N(B6)=0),"",C6/B6) | J6: Latest month entered | K6: =IF(COUNT(D5:D17)=0,"",LOOKUP(2,1/(D5:D17<>""),A5:A17))
A7: Feb 2027 | B7: =Balances!F47 | C7: =Balances!F48 | D7: =Balances!F49 | E7: =IF(OR(D7="",D6=""),"",D7-D6) | F7: =IF(OR(D7="",$D$5=""),"",D7-$D$5) | G7: =IF(OR(D7="",Settings!$C$4<=0),"",D7/Settings!$C$4) | H7: =IF(OR(B7="",N(B7)=0),"",C7/B7) | J7: Change since start | K7: =IF(OR(K5="",D5=""),"",K5-D5)
A8: Mar 2027 | B8: =Balances!G47 | C8: =Balances!G48 | D8: =Balances!G49 | E8: =IF(OR(D8="",D7=""),"",D8-D7) | F8: =IF(OR(D8="",$D$5=""),"",D8-$D$5) | G8: =IF(OR(D8="",Settings!$C$4<=0),"",D8/Settings!$C$4) | H8: =IF(OR(B8="",N(B8)=0),"",C8/B8) | J8: Goal for Dec 31, 2027 | K8: =Settings!C4 -> 0
A9: Apr 2027 | B9: =Balances!H47 | C9: =Balances!H48 | D9: =Balances!H49 | E9: =IF(OR(D9="",D8=""),"",D9-D8) | F9: =IF(OR(D9="",$D$5=""),"",D9-$D$5) | G9: =IF(OR(D9="",Settings!$C$4<=0),"",D9/Settings!$C$4) | H9: =IF(OR(B9="",N(B9)=0),"",C9/B9) | J9: Still to go | K9: =IF(OR(K5="",K8<=0),"",MAX(0,K8-K5))
A10: May 2027 | B10: =Balances!I47 | C10: =Balances!I48 | D10: =Balances!I49 | E10: =IF(OR(D10="",D9=""),"",D10-D9) | F10: =IF(OR(D10="",$D$5=""),"",D10-$D$5) | G10: =IF(OR(D10="",Settings!$C$4<=0),"",D10/Settings!$C$4) | H10: =IF(OR(B10="",N(B10)=0),"",C10/B10) | J10: Best month (biggest increase) | K10: =IF(COUNT(E6:E17)=0,"",MAX(E6:E17))
A11: Jun 2027 | B11: =Balances!J47 | C11: =Balances!J48 | D11: =Balances!J49 | E11: =IF(OR(D11="",D10=""),"",D11-D10) | F11: =IF(OR(D11="",$D$5=""),"",D11-$D$5) | G11: =IF(OR(D11="",Settings!$C$4<=0),"",D11/Settings!$C$4) | H11: =IF(OR(B11="",N(B11)=0),"",C11/B11) | J11: Average monthly change | K11: =IF(COUNT(E6:E17)=0,"",AVERAGE(E6:E17))
A12: Jul 2027 | B12: =Balances!K47 | C12: =Balances!K48 | D12: =Balances!K49 | E12: =IF(OR(D12="",D11=""),"",D12-D11) | F12: =IF(OR(D12="",$D$5=""),"",D12-$D$5) | G12: =IF(OR(D12="",Settings!$C$4<=0),"",D12/Settings!$C$4) | H12: =IF(OR(B12="",N(B12)=0),"",C12/B12) | J12: Emergency fund vs target | K12: ='By Category'!O23
A13: Aug 2027 | B13: =Balances!L47 | C13: =Balances!L48 | D13: =Balances!L49 | E13: =IF(OR(D13="",D12=""),"",D13-D12) | F13: =IF(OR(D13="",$D$5=""),"",D13-$D$5) | G13: =IF(OR(D13="",Settings!$C$4<=0),"",D13/Settings!$C$4) | H13: =IF(OR(B13="",N(B13)=0),"",C13/B13)
A14: Sep 2027 | B14: =Balances!M47 | C14: =Balances!M48 | D14: =Balances!M49 | E14: =IF(OR(D14="",D13=""),"",D14-D13) | F14: =IF(OR(D14="",$D$5=""),"",D14-$D$5) | G14: =IF(OR(D14="",Settings!$C$4<=0),"",D14/Settings!$C$4) | H14: =IF(OR(B14="",N(B14)=0),"",C14/B14)
A15: Oct 2027 | B15: =Balances!N47 | C15: =Balances!N48 | D15: =Balances!N49 | E15: =IF(OR(D15="",D14=""),"",D15-D14) | F15: =IF(OR(D15="",$D$5=""),"",D15-$D$5) | G15: =IF(OR(D15="",Settings!$C$4<=0),"",D15/Settings!$C$4) | H15: =IF(OR(B15="",N(B15)=0),"",C15/B15)
A16: Nov 2027 | B16: =Balances!O47 | C16: =Balances!O48 | D16: =Balances!O49 | E16: =IF(OR(D16="",D15=""),"",D16-D15) | F16: =IF(OR(D16="",$D$5=""),"",D16-$D$5) | G16: =IF(OR(D16="",Settings!$C$4<=0),"",D16/Settings!$C$4) | H16: =IF(OR(B16="",N(B16)=0),"",C16/B16)
A17: Dec 2027 | B17: =Balances!P47 | C17: =Balances!P48 | D17: =Balances!P49 | E17: =IF(OR(D17="",D16=""),"",D17-D16) | F17: =IF(OR(D17="",$D$5=""),"",D17-$D$5) | G17: =IF(OR(D17="",Settings!$C$4<=0),"",D17/Settings!$C$4) | H17: =IF(OR(B17="",N(B17)=0),"",C17/B17)

Sheet By Category
A1: By Category - where your money sits (and what you owe)
A3: Category | B3: Start | C3: Jan | D3: Feb | E3: Mar | F3: Apr | G3: May | H3: Jun | I3: Jul | J3: Aug | K3: Sep | L3: Oct | M3: Nov | N3: Dec | O3: Change since start
A4: ASSETS
A5: Cash & Checking | B5: =IF(COUNT(Balances!D$6:D$45)=0,"",SUMIF(Balances!$C$6:$C$45,$A5,Balances!D$6:D$45)) | C5: =IF(COUNT(Balances!E$6:E$45)=0,"",SUMIF(Balances!$C$6:$C$45,$A5,Balances!E$6:E$45)) | D5: =IF(COUNT(Balances!F$6:F$45)=0,"",SUMIF(Balances!$C$6:$C$45,$A5,Balances!F$6:F$45)) | E5: =IF(COUNT(Balances!G$6:G$45)=0,"",SUMIF(Balances!$C$6:$C$45,$A5,Balances!G$6:G$45)) | F5: =IF(COUNT(Balances!H$6:H$45)=0,"",SUMIF(Balances!$C$6:$C$45,$A5,Balances!H$6:H$45)) | G5: =IF(COUNT(Balances!I$6:I$45)=0,"",SUMIF(Balances!$C$6:$C$45,$A5,Balances!I$6:I$45)) | H5: =IF(COUNT(Balances!J$6:J$45)=0,"",SUMIF(Balances!$C$6:$C$45,$A5,Balances!J$6:J$45)) | I5: =IF(COUNT(Balances!K$6:K$45)=0,"",SUMIF(Balances!$C$6:$C$45,$A5,Balances!K$6:K$45)) | ... N5: =IF(COUNT(Balances!P$6:P$45)=0,"",SUMIF(Balances!$C$6:$C$45,$A5,Balances!P$6:P$45)) | O5: =IFERROR(LOOKUP(2,1/(B5:N5<>""),B5:N5)-B5,"")
A6: Savings & Emergency Fund | B6: =IF(COUNT(Balances!D$6:D$45)=0,"",SUMIF(Balances!$C$6:$C$45,$A6,Balances!D$6:D$45)) | C6: =IF(COUNT(Balances!E$6:E$45)=0,"",SUMIF(Balances!$C$6:$C$45,$A6,Balances!E$6:E$45)) | D6: =IF(COUNT(Balances!F$6:F$45)=0,"",SUMIF(Balances!$C$6:$C$45,$A6,Balances!F$6:F$45)) | E6: =IF(COUNT(Balances!G$6:G$45)=0,"",SUMIF(Balances!$C$6:$C$45,$A6,Balances!G$6:G$45)) | F6: =IF(COUNT(Balances!H$6:H$45)=0,"",SUMIF(Balances!$C$6:$C$45,$A6,Balances!H$6:H$45)) | G6: =IF(COUNT(Balances!I$6:I$45)=0,"",SUMIF(Balances!$C$6:$C$45,$A6,Balances!I$6:I$45)) | H6: =IF(COUNT(Balances!J$6:J$45)=0,"",SUMIF(Balances!$C$6:$C$45,$A6,Balances!J$6:J$45)) | I6: =IF(COUNT(Balances!K$6:K$45)=0,"",SUMIF(Balances!$C$6:$C$45,$A6,Balances!K$6:K$45)) | ... N6: =IF(COUNT(Balances!P$6:P$45)=0,"",SUMIF(Balances!$C$6:$C$45,$A6,Balances!P$6:P$45)) | O6: =IFERROR(LOOKUP(2,1/(B6:N6<>""),B6:N6)-B6,"")
A7: Investments | B7: =IF(COUNT(Balances!D$6:D$45)=0,"",SUMIF(Balances!$C$6:$C$45,$A7,Balances!D$6:D$45)) | C7: =IF(COUNT(Balances!E$6:E$45)=0,"",SUMIF(Balances!$C$6:$C$45,$A7,Balances!E$6:E$45)) | D7: =IF(COUNT(Balances!F$6:F$45)=0,"",SUMIF(Balances!$C$6:$C$45,$A7,Balances!F$6:F$45)) | E7: =IF(COUNT(Balances!G$6:G$45)=0,"",SUMIF(Balances!$C$6:$C$45,$A7,Balances!G$6:G$45)) | F7: =IF(COUNT(Balances!H$6:H$45)=0,"",SUMIF(Balances!$C$6:$C$45,$A7,Balances!H$6:H$45)) | G7: =IF(COUNT(Balances!I$6:I$45)=0,"",SUMIF(Balances!$C$6:$C$45,$A7,Balances!I$6:I$45)) | H7: =IF(COUNT(Balances!J$6:J$45)=0,"",SUMIF(Balances!$C$6:$C$45,$A7,Balances!J$6:J$45)) | I7: =IF(COUNT(Balances!K$6:K$45)=0,"",SUMIF(Balances!$C$6:$C$45,$A7,Balances!K$6:K$45)) | ... N7: =IF(COUNT(Balances!P$6:P$45)=0,"",SUMIF(Balances!$C$6:$C$45,$A7,Balances!P$6:P$45)) | O7: =IFERROR(LOOKUP(2,1/(B7:N7<>""),B7:N7)-B7,"")
A8: Retirement | B8: =IF(COUNT(Balances!D$6:D$45)=0,"",SUMIF(Balances!$C$6:$C$45,$A8,Balances!D$6:D$45)) | C8: =IF(COUNT(Balances!E$6:E$45)=0,"",SUMIF(Balances!$C$6:$C$45,$A8,Balances!E$6:E$45)) | D8: =IF(COUNT(Balances!F$6:F$45)=0,"",SUMIF(Balances!$C$6:$C$45,$A8,Balances!F$6:F$45)) | E8: =IF(COUNT(Balances!G$6:G$45)=0,"",SUMIF(Balances!$C$6:$C$45,$A8,Balances!G$6:G$45)) | F8: =IF(COUNT(Balances!H$6:H$45)=0,"",SUMIF(Balances!$C$6:$C$45,$A8,Balances!H$6:H$45)) | G8: =IF(COUNT(Balances!I$6:I$45)=0,"",SUMIF(Balances!$C$6:$C$45,$A8,Balances!I$6:I$45)) | H8: =IF(COUNT(Balances!J$6:J$45)=0,"",SUMIF(Balances!$C$6:$C$45,$A8,Balances!J$6:J$45)) | I8: =IF(COUNT(Balances!K$6:K$45)=0,"",SUMIF(Balances!$C$6:$C$45,$A8,Balances!K$6:K$45)) | ... N8: =IF(COUNT(Balances!P$6:P$45)=0,"",SUMIF(Balances!$C$6:$C$45,$A8,Balances!P$6:P$45)) | O8: =IFERROR(LOOKUP(2,1/(B8:N8<>""),B8:N8)-B8,"")
A9: Home / Property | B9: =IF(COUNT(Balances!D$6:D$45)=0,"",SUMIF(Balances!$C$6:$C$45,$A9,Balances!D$6:D$45)) | C9: =IF(COUNT(Balances!E$6:E$45)=0,"",SUMIF(Balances!$C$6:$C$45,$A9,Balances!E$6:E$45)) | D9: =IF(COUNT(Balances!F$6:F$45)=0,"",SUMIF(Balances!$C$6:$C$45,$A9,Balances!F$6:F$45)) | E9: =IF(COUNT(Balances!G$6:G$45)=0,"",SUMIF(Balances!$C$6:$C$45,$A9,Balances!G$6:G$45)) | F9: =IF(COUNT(Balances!H$6:H$45)=0,"",SUMIF(Balances!$C$6:$C$45,$A9,Balances!H$6:H$45)) | G9: =IF(COUNT(Balances!I$6:I$45)=0,"",SUMIF(Balances!$C$6:$C$45,$A9,Balances!I$6:I$45)) | H9: =IF(COUNT(Balances!J$6:J$45)=0,"",SUMIF(Balances!$C$6:$C$45,$A9,Balances!J$6:J$45)) | I9: =IF(COUNT(Balances!K$6:K$45)=0,"",SUMIF(Balances!$C$6:$C$45,$A9,Balances!K$6:K$45)) | ... N9: =IF(COUNT(Balances!P$6:P$45)=0,"",SUMIF(Balances!$C$6:$C$45,$A9,Balances!P$6:P$45)) | O9: =IFERROR(LOOKUP(2,1/(B9:N9<>""),B9:N9)-B9,"")
A10: Vehicles | B10: =IF(COUNT(Balances!D$6:D$45)=0,"",SUMIF(Balances!$C$6:$C$45,$A10,Balances!D$6:D$45)) | C10: =IF(COUNT(Balances!E$6:E$45)=0,"",SUMIF(Balances!$C$6:$C$45,$A10,Balances!E$6:E$45)) | D10: =IF(COUNT(Balances!F$6:F$45)=0,"",SUMIF(Balances!$C$6:$C$45,$A10,Balances!F$6:F$45)) | E10: =IF(COUNT(Balances!G$6:G$45)=0,"",SUMIF(Balances!$C$6:$C$45,$A10,Balances!G$6:G$45)) | F10: =IF(COUNT(Balances!H$6:H$45)=0,"",SUMIF(Balances!$C$6:$C$45,$A10,Balances!H$6:H$45)) | G10: =IF(COUNT(Balances!I$6:I$45)=0,"",SUMIF(Balances!$C$6:$C$45,$A10,Balances!I$6:I$45)) | H10: =IF(COUNT(Balances!J$6:J$45)=0,"",SUMIF(Balances!$C$6:$C$45,$A10,Balances!J$6:J$45)) | I10: =IF(COUNT(Balances!K$6:K$45)=0,"",SUMIF(Balances!$C$6:$C$45,$A10,Balances!K$6:K$45)) | ... N10: =IF(COUNT(Balances!P$6:P$45)=0,"",SUMIF(Balances!$C$6:$C$45,$A10,Balances!P$6:P$45)) | O10: =IFERROR(LOOKUP(2,1/(B10:N10<>""),B10:N10)-B10,"")
A11: Other Assets | B11: =IF(COUNT(Balances!D$6:D$45)=0,"",SUMIF(Balances!$C$6:$C$45,$A11,Balances!D$6:D$45)) | C11: =IF(COUNT(Balances!E$6:E$45)=0,"",SUMIF(Balances!$C$6:$C$45,$A11,Balances!E$6:E$45)) | D11: =IF(COUNT(Balances!F$6:F$45)=0,"",SUMIF(Balances!$C$6:$C$45,$A11,Balances!F$6:F$45)) | E11: =IF(COUNT(Balances!G$6:G$45)=0,"",SUMIF(Balances!$C$6:$C$45,$A11,Balances!G$6:G$45)) | F11: =IF(COUNT(Balances!H$6:H$45)=0,"",SUMIF(Balances!$C$6:$C$45,$A11,Balances!H$6:H$45)) | G11: =IF(COUNT(Balances!I$6:I$45)=0,"",SUMIF(Balances!$C$6:$C$45,$A11,Balances!I$6:I$45)) | H11: =IF(COUNT(Balances!J$6:J$45)=0,"",SUMIF(Balances!$C$6:$C$45,$A11,Balances!J$6:J$45)) | I11: =IF(COUNT(Balances!K$6:K$45)=0,"",SUMIF(Balances!$C$6:$C$45,$A11,Balances!K$6:K$45)) | ... N11: =IF(COUNT(Balances!P$6:P$45)=0,"",SUMIF(Balances!$C$6:$C$45,$A11,Balances!P$6:P$45)) | O11: =IFERROR(LOOKUP(2,1/(B11:N11<>""),B11:N11)-B11,"")
A12: Total assets | B12: =IF(COUNT(B5:B11)=0,"",SUM(B5:B11)) | C12: =IF(COUNT(C5:C11)=0,"",SUM(C5:C11)) | D12: =IF(COUNT(D5:D11)=0,"",SUM(D5:D11)) | E12: =IF(COUNT(E5:E11)=0,"",SUM(E5:E11)) | F12: =IF(COUNT(F5:F11)=0,"",SUM(F5:F11)) | G12: =IF(COUNT(G5:G11)=0,"",SUM(G5:G11)) | H12: =IF(COUNT(H5:H11)=0,"",SUM(H5:H11)) | I12: =IF(COUNT(I5:I11)=0,"",SUM(I5:I11)) | ... O12: =IF(COUNT(O5:O11)=0,"",SUM(O5:O11))
A14: DEBTS
A15: Credit Cards | B15: =IF(COUNT(Balances!D$6:D$45)=0,"",SUMIF(Balances!$C$6:$C$45,$A15,Balances!D$6:D$45)) | C15: =IF(COUNT(Balances!E$6:E$45)=0,"",SUMIF(Balances!$C$6:$C$45,$A15,Balances!E$6:E$45)) | D15: =IF(COUNT(Balances!F$6:F$45)=0,"",SUMIF(Balances!$C$6:$C$45,$A15,Balances!F$6:F$45)) | E15: =IF(COUNT(Balances!G$6:G$45)=0,"",SUMIF(Balances!$C$6:$C$45,$A15,Balances!G$6:G$45)) | F15: =IF(COUNT(Balances!H$6:H$45)=0,"",SUMIF(Balances!$C$6:$C$45,$A15,Balances!H$6:H$45)) | G15: =IF(COUNT(Balances!I$6:I$45)=0,"",SUMIF(Balances!$C$6:$C$45,$A15,Balances!I$6:I$45)) | H15: =IF(COUNT(Balances!J$6:J$45)=0,"",SUMIF(Balances!$C$6:$C$45,$A15,Balances!J$6:J$45)) | I15: =IF(COUNT(Balances!K$6:K$45)=0,"",SUMIF(Balances!$C$6:$C$45,$A15,Balances!K$6:K$45)) | ... N15: =IF(COUNT(Balances!P$6:P$45)=0,"",SUMIF(Balances!$C$6:$C$45,$A15,Balances!P$6:P$45)) | O15: =IFERROR(LOOKUP(2,1/(B15:N15<>""),B15:N15)-B15,"")
A16: Student Loans | B16: =IF(COUNT(Balances!D$6:D$45)=0,"",SUMIF(Balances!$C$6:$C$45,$A16,Balances!D$6:D$45)) | C16: =IF(COUNT(Balances!E$6:E$45)=0,"",SUMIF(Balances!$C$6:$C$45,$A16,Balances!E$6:E$45)) | D16: =IF(COUNT(Balances!F$6:F$45)=0,"",SUMIF(Balances!$C$6:$C$45,$A16,Balances!F$6:F$45)) | E16: =IF(COUNT(Balances!G$6:G$45)=0,"",SUMIF(Balances!$C$6:$C$45,$A16,Balances!G$6:G$45)) | F16: =IF(COUNT(Balances!H$6:H$45)=0,"",SUMIF(Balances!$C$6:$C$45,$A16,Balances!H$6:H$45)) | G16: =IF(COUNT(Balances!I$6:I$45)=0,"",SUMIF(Balances!$C$6:$C$45,$A16,Balances!I$6:I$45)) | H16: =IF(COUNT(Balances!J$6:J$45)=0,"",SUMIF(Balances!$C$6:$C$45,$A16,Balances!J$6:J$45)) | I16: =IF(COUNT(Balances!K$6:K$45)=0,"",SUMIF(Balances!$C$6:$C$45,$A16,Balances!K$6:K$45)) | ... N16: =IF(COUNT(Balances!P$6:P$45)=0,"",SUMIF(Balances!$C$6:$C$45,$A16,Balances!P$6:P$45)) | O16: =IFERROR(LOOKUP(2,1/(B16:N16<>""),B16:N16)-B16,"")
A17: Car Loans | B17: =IF(COUNT(Balances!D$6:D$45)=0,"",SUMIF(Balances!$C$6:$C$45,$A17,Balances!D$6:D$45)) | C17: =IF(COUNT(Balances!E$6:E$45)=0,"",SUMIF(Balances!$C$6:$C$45,$A17,Balances!E$6:E$45)) | D17: =IF(COUNT(Balances!F$6:F$45)=0,"",SUMIF(Balances!$C$6:$C$45,$A17,Balances!F$6:F$45)) | E17: =IF(COUNT(Balances!G$6:G$45)=0,"",SUMIF(Balances!$C$6:$C$45,$A17,Balances!G$6:G$45)) | F17: =IF(COUNT(Balances!H$6:H$45)=0,"",SUMIF(Balances!$C$6:$C$45,$A17,Balances!H$6:H$45)) | G17: =IF(COUNT(Balances!I$6:I$45)=0,"",SUMIF(Balances!$C$6:$C$45,$A17,Balances!I$6:I$45)) | H17: =IF(COUNT(Balances!J$6:J$45)=0,"",SUMIF(Balances!$C$6:$C$45,$A17,Balances!J$6:J$45)) | I17: =IF(COUNT(Balances!K$6:K$45)=0,"",SUMIF(Balances!$C$6:$C$45,$A17,Balances!K$6:K$45)) | ... N17: =IF(COUNT(Balances!P$6:P$45)=0,"",SUMIF(Balances!$C$6:$C$45,$A17,Balances!P$6:P$45)) | O17: =IFERROR(LOOKUP(2,1/(B17:N17<>""),B17:N17)-B17,"")
A18: Mortgage | B18: =IF(COUNT(Balances!D$6:D$45)=0,"",SUMIF(Balances!$C$6:$C$45,$A18,Balances!D$6:D$45)) | C18: =IF(COUNT(Balances!E$6:E$45)=0,"",SUMIF(Balances!$C$6:$C$45,$A18,Balances!E$6:E$45)) | D18: =IF(COUNT(Balances!F$6:F$45)=0,"",SUMIF(Balances!$C$6:$C$45,$A18,Balances!F$6:F$45)) | E18: =IF(COUNT(Balances!G$6:G$45)=0,"",SUMIF(Balances!$C$6:$C$45,$A18,Balances!G$6:G$45)) | F18: =IF(COUNT(Balances!H$6:H$45)=0,"",SUMIF(Balances!$C$6:$C$45,$A18,Balances!H$6:H$45)) | G18: =IF(COUNT(Balances!I$6:I$45)=0,"",SUMIF(Balances!$C$6:$C$45,$A18,Balances!I$6:I$45)) | H18: =IF(COUNT(Balances!J$6:J$45)=0,"",SUMIF(Balances!$C$6:$C$45,$A18,Balances!J$6:J$45)) | I18: =IF(COUNT(Balances!K$6:K$45)=0,"",SUMIF(Balances!$C$6:$C$45,$A18,Balances!K$6:K$45)) | ... N18: =IF(COUNT(Balances!P$6:P$45)=0,"",SUMIF(Balances!$C$6:$C$45,$A18,Balances!P$6:P$45)) | O18: =IFERROR(LOOKUP(2,1/(B18:N18<>""),B18:N18)-B18,"")
A19: Personal Loans | B19: =IF(COUNT(Balances!D$6:D$45)=0,"",SUMIF(Balances!$C$6:$C$45,$A19,Balances!D$6:D$45)) | C19: =IF(COUNT(Balances!E$6:E$45)=0,"",SUMIF(Balances!$C$6:$C$45,$A19,Balances!E$6:E$45)) | D19: =IF(COUNT(Balances!F$6:F$45)=0,"",SUMIF(Balances!$C$6:$C$45,$A19,Balances!F$6:F$45)) | E19: =IF(COUNT(Balances!G$6:G$45)=0,"",SUMIF(Balances!$C$6:$C$45,$A19,Balances!G$6:G$45)) | F19: =IF(COUNT(Balances!H$6:H$45)=0,"",SUMIF(Balances!$C$6:$C$45,$A19,Balances!H$6:H$45)) | G19: =IF(COUNT(Balances!I$6:I$45)=0,"",SUMIF(Balances!$C$6:$C$45,$A19,Balances!I$6:I$45)) | H19: =IF(COUNT(Balances!J$6:J$45)=0,"",SUMIF(Balances!$C$6:$C$45,$A19,Balances!J$6:J$45)) | I19: =IF(COUNT(Balances!K$6:K$45)=0,"",SUMIF(Balances!$C$6:$C$45,$A19,Balances!K$6:K$45)) | ... N19: =IF(COUNT(Balances!P$6:P$45)=0,"",SUMIF(Balances!$C$6:$C$45,$A19,Balances!P$6:P$45)) | O19: =IFERROR(LOOKUP(2,1/(B19:N19<>""),B19:N19)-B19,"")
A20: Medical / Other Debt | B20: =IF(COUNT(Balances!D$6:D$45)=0,"",SUMIF(Balances!$C$6:$C$45,$A20,Balances!D$6:D$45)) | C20: =IF(COUNT(Balances!E$6:E$45)=0,"",SUMIF(Balances!$C$6:$C$45,$A20,Balances!E$6:E$45)) | D20: =IF(COUNT(Balances!F$6:F$45)=0,"",SUMIF(Balances!$C$6:$C$45,$A20,Balances!F$6:F$45)) | E20: =IF(COUNT(Balances!G$6:G$45)=0,"",SUMIF(Balances!$C$6:$C$45,$A20,Balances!G$6:G$45)) | F20: =IF(COUNT(Balances!H$6:H$45)=0,"",SUMIF(Balances!$C$6:$C$45,$A20,Balances!H$6:H$45)) | G20: =IF(COUNT(Balances!I$6:I$45)=0,"",SUMIF(Balances!$C$6:$C$45,$A20,Balances!I$6:I$45)) | H20: =IF(COUNT(Balances!J$6:J$45)=0,"",SUMIF(Balances!$C$6:$C$45,$A20,Balances!J$6:J$45)) | I20: =IF(COUNT(Balances!K$6:K$45)=0,"",SUMIF(Balances!$C$6:$C$45,$A20,Balances!K$6:K$45)) | ... N20: =IF(COUNT(Balances!P$6:P$45)=0,"",SUMIF(Balances!$C$6:$C$45,$A20,Balances!P$6:P$45)) | O20: =IFERROR(LOOKUP(2,1/(B20:N20<>""),B20:N20)-B20,"")
A21: Total debts | B21: =IF(COUNT(B15:B20)=0,"",SUM(B15:B20)) | C21: =IF(COUNT(C15:C20)=0,"",SUM(C15:C20)) | D21: =IF(COUNT(D15:D20)=0,"",SUM(D15:D20)) | E21: =IF(COUNT(E15:E20)=0,"",SUM(E15:E20)) | F21: =IF(COUNT(F15:F20)=0,"",SUM(F15:F20)) | G21: =IF(COUNT(G15:G20)=0,"",SUM(G15:G20)) | H21: =IF(COUNT(H15:H20)=0,"",SUM(H15:H20)) | I21: =IF(COUNT(I15:I20)=0,"",SUM(I15:I20)) | ... O21: =IF(COUNT(O15:O20)=0,"",SUM(O15:O20))
A23: Emergency fund: latest 'Savings & Emergency Fund' vs target on Settings | N23: % of target | O23: =IF(OR(Settings!C5<=0,COUNT(B6:N6)=0),"",LOOKUP(2,1/(B6:N6<>""),B6:N6)/Settings!C5)

Sheet Lists
A1: Type | B1: Asset categories | C1: Debt categories | D1: All categories
A2: Asset | B2: Cash & Checking | C2: Credit Cards | D2: Cash & Checking
A3: Debt | B3: Savings & Emergency Fund | C3: Student Loans | D3: Savings & Emergency Fund
B4: Investments | C4: Car Loans | D4: Investments
B5: Retirement | C5: Mortgage | D5: Retirement
B6: Home / Property | C6: Personal Loans | D6: Home / Property
B7: Vehicles | C7: Medical / Other Debt | D7: Vehicles
B8: Other Assets | D8: Other Assets
D9: Credit Cards
D10: Student Loans
D11: Car Loans
D12: Mortgage
D13: Personal Loans
D14: Medical / Other Debt
